gist_neko/__init__.py
gist_neko/__main__.py
gist_neko/cli.py
gist_neko/download.py
gist_neko/version.py
gist_neko-1.27.dist-info/licenses/LICENSE
gist_neko-1.27.dist-info/WHEEL
gist_neko-1.27.dist-info/entry_points.txt
gist_neko-1.27.dist-info/METADATA
gist_neko-1.27.dist-info/RECORD
