Metadata-Version: 2.4
Name: gist-neko
Version: 1.27
Summary: CLI for downloading all gists from a specified user.
Keywords: python,gist downloader,downloader,gist,gist-neko,kuroneko
Author: NecRaul
Author-email: NecRaul <necraul@kuroneko.dev>
License-Expression: LGPL-2.1-only
License-File: LICENSE
Classifier: Development Status :: 5 - Production/Stable
Classifier: Environment :: Console
Classifier: Intended Audience :: Developers
Classifier: Natural Language :: English
Classifier: Operating System :: OS Independent
Classifier: Programming Language :: Python :: 3 :: Only
Classifier: Programming Language :: Python :: 3.10
Classifier: Programming Language :: Python :: 3.11
Classifier: Programming Language :: Python :: 3.12
Classifier: Programming Language :: Python :: 3.13
Classifier: Programming Language :: Python :: 3.14
Classifier: Topic :: Internet :: WWW/HTTP
Requires-Dist: requests>=2.32.5
Requires-Python: >=3.10
Project-URL: Homepage, https://github.com/NecRaul/gist-neko
Project-URL: Documentation, https://github.com/NecRaul/gist-neko#readme
Project-URL: Repository, https://github.com/NecRaul/gist-neko
Project-URL: Issues, https://github.com/NecRaul/gist-neko/issues
